LICENSE
MANIFEST.in
README.rst
requirements.txt
setup.py
Flask_Project.egg-info/PKG-INFO
Flask_Project.egg-info/SOURCES.txt
Flask_Project.egg-info/dependency_links.txt
Flask_Project.egg-info/entry_points.txt
Flask_Project.egg-info/requires.txt
Flask_Project.egg-info/top_level.txt
flask_project/__init__.py
flask_project/command.py
flask_project/importing.py
flask_project/log.py
flask_project/utils.py
flask_project/templates/__init__.py
flask_project/templates/default/.gitignore
flask_project/templates/default/README.md
flask_project/templates/default/manager.py
flask_project/templates/default/requirements.txt
flask_project/templates/default/run.sh
flask_project/templates/default/test_run.sh
flask_project/templates/default/wsgi.py
flask_project/templates/default/config/__init__.py
flask_project/templates/default/config/development.py
flask_project/templates/default/config/production.py
flask_project/templates/default/config/testing.py
flask_project/templates/default/data/.gitignore
flask_project/templates/default/data/db/.gitkeep
flask_project/templates/default/data/uploads/.gitkeep
flask_project/templates/default/deploy/gunicorn.conf
flask_project/templates/default/deploy/nginx.conf
flask_project/templates/default/deploy/supervisor.conf
flask_project/templates/default/scripts/env.local.template.sh
flask_project/templates/default/scripts/env_conf.sh
flask_project/templates/default/tests/__init__.py
flask_project/templates/default/tests/suite.py
flask_project/templates/default/tests/test_site.py
flask_project/templates/default/web_site/__init__.py
flask_project/templates/default/web_site/email.py
flask_project/templates/default/web_site/filters.py
flask_project/templates/default/web_site/utils.py
flask_project/templates/default/web_site/admin/__init__.py
flask_project/templates/default/web_site/admin/views.py
flask_project/templates/default/web_site/main/__init__.py
flask_project/templates/default/web_site/main/views.py
flask_project/templates/default/web_site/static/favicon.ico
flask_project/templates/default/web_site/static/css/bootstrap-theme.css
flask_project/templates/default/web_site/static/css/bootstrap-theme.css.map
