Metadata-Version: 1.1
Name: Flask-Project
Version: 0.1.0
Summary: Flask project template generator.
Home-page: https://github.com/hyperwood/Flask-Project
Author: hyperwood
Author-email: hyperwood.yw@gmail.com
License: MIT
Keywords: flask sample template generator
Platform: UNKNOWN
Classifier: Development Status :: 3 - Alpha
Classifier: Environment :: Web Environment
Classifier: Intended Audience :: Developers
Classifier: License :: OSI Approved :: MIT License
Classifier: Operating System :: OS Independent
Classifier: Programming Language :: Python :: 2.7
Classifier: Topic :: Internet :: WWW/HTTP :: Dynamic Content
Classifier: Topic :: Software Development :: Libraries :: Python Modules
